switch_inputs/ConvertDatetime.py
switch_inputs/__init__.py
switch_inputs/__main__.py
switch_inputs/__version__.py
switch_inputs/bioenergy_clean.py
switch_inputs/bioenergy_process.py
switch_inputs/cli.py
switch_inputs/context.py
switch_inputs/create_inputs.py
switch_inputs/geothermal_clean.py
switch_inputs/outputs_process.py
switch_inputs/renewable_ninja.py
switch_inputs/tmp.py
switch_inputs/utils.py
switch_inputs-0.7.0.dist-info/LICENCE
switch_inputs-0.7.0.dist-info/METADATA
switch_inputs-0.7.0.dist-info/WHEEL
switch_inputs-0.7.0.dist-info/entry_points.txt
switch_inputs-0.7.0.dist-info/top_level.txt
switch_inputs-0.7.0.dist-info/RECORD
