Metadata-Version: 2.1
Name: switch-inputs
Version: 0.7.0
Summary: Create input files for switch
Home-page: https://github.com/pypa/example-project
Author: pesap
Author-email: pesapsanchez@gmail.com
License: UNKNOWN
Platform: UNKNOWN
Classifier: Programming Language :: Python :: 3
Classifier: License :: OSI Approved :: MIT License
Classifier: Operating System :: OS Independent
Classifier: Development Status :: 3 - Alpha
Requires-Dist: tqdm
Requires-Dist: pandas
Requires-Dist: requests
Requires-Dist: click
Requires-Dist: pyyaml
